Metadata-Version: 2.1
Name: sqlglot-doris
Version: 1.3.0
Summary: An easily customizable SQL parser and transpiler
Home-page: https://github.com/tobymao/sqlglot
Author: Toby Mao
Author-email: toby.mao@gmail.com
License: MIT
Classifier: Development Status :: 5 - Production/Stable
Classifier: Intended Audience :: Developers
Classifier: Intended Audience :: Science/Research
Classifier: License :: OSI Approved :: MIT License
Classifier: Operating System :: OS Independent
Classifier: Programming Language :: SQL
Classifier: Programming Language :: Python :: 3 :: Only
Requires-Python: >=3.7
License-File: LICENSE
License-File: LICENSE_SQLGLOT
Provides-Extra: dev
Requires-Dist: duckdb>=0.6; extra == "dev"
Requires-Dist: mypy; extra == "dev"
Requires-Dist: pandas; extra == "dev"
Requires-Dist: pandas-stubs; extra == "dev"
Requires-Dist: python-dateutil; extra == "dev"
Requires-Dist: pytz; extra == "dev"
Requires-Dist: pdoc; extra == "dev"
Requires-Dist: pre-commit; extra == "dev"
Requires-Dist: ruff==0.4.3; extra == "dev"
Requires-Dist: types-python-dateutil; extra == "dev"
Requires-Dist: types-pytz; extra == "dev"
Requires-Dist: typing_extensions; extra == "dev"
Requires-Dist: maturin<2.0,>=1.4; extra == "dev"
Provides-Extra: rs
Requires-Dist: sqlglotrs==0.2.12; extra == "rs"
